{"object": [{"link": "dalaeyes.official", "orders": [{"link": "dalaeye-v3", "orders": 14.0}, {"link": "dalaeye-v3", "orders": 4.0}], "visitors": 252, "toCart": 31, "Checkout": 19}, {"link": "dalaeyes.official", "orders": [{"link": "dalaeye-v3", "orders": 13.0}, {"link": "dalaeye-v3", "orders": 3.0}], "visitors": 223, "toCart": 27, "Checkout": 17}, {"link": "dalaeyes.official", "orders": [{"link": "dalaeye-v3", "orders": 14.0}, {"link": "dalaeye-v3", "orders": 3.0}], "visitors": 238, "toCart": 29, "Checkout": 18}, {"link": "dalaeyes.official", "orders": [{"link": "dalaeye-v3", "orders": 13.0}, {"link": "dalaeye-v3", "orders": 3.0}], "visitors": 223, "toCart": 27, "Checkout": 17}, {"link": "dalaeyes.official", "orders": [{"link": "dalaeye-v3", "orders": 13.0}, {"link": "dalaeye-v3", "orders": 3.0}], "visitors": 223, "toCart": 27, "Checkout": 17}, {"link": "dalaeyes.official", "orders": [{"link": "dalaeye-v3", "orders": 13.0}, {"link": "dalaeye-v3", "orders": 3.0}], "visitors": 223, "toCart": 27, "Checkout": 17}, {"link": "dalaeyes.official", "orders": [{"link": "dalaeye-v3", "orders": 7.0}, {"link": "dalaeye-v3", "orders": 2.0}], "visitors": 126, "toCart": 16, "Checkout": 10}, {"link": "dalaeyes.official", "orders": [{"link": "dalaeye-v3", "orders": 6.0}, {"link": "dalaeye-v3", "orders": 1.0}], "visitors": 99, "toCart": 12, "Checkout": 8}, {"link": "dalaeyes.official", "orders": [{"link": "dalaeye-v3", "orders": 5.0}, {"link": "dalaeye-v3", "orders": 1.0}], "visitors": 84, "toCart": 11, "Checkout": 7}, {"link": "dalaeyes.official", "orders": [{"link": "dalaeye-v3", "orders": 7.0}, {"link": "dalaeye-v3", "orders": 2.0}], "visitors": 126, "toCart": 16, "Checkout": 10}, {"link": "dalaeyes.official", "orders": [{"link": "dalaeye-v3", "orders": 8.0}, {"link": "dalaeye-v3", "orders": 2.0}], "visitors": 140, "toCart": 17, "Checkout": 11}, {"link": "dalaeyes.official", "orders": [{"link": "dalaeye-v3", "orders": 6.0}, {"link": "dalaeye-v3", "orders": 1.0}], "visitors": 99, "toCart": 12, "Checkout": 8}, {"link": "dalaeyes.official", "orders": [{"link": "dalaeye-v3", "orders": 7.0}, {"link": "dalaeye-v3", "orders": 2.0}], "visitors": 126, "toCart": 16, "Checkout": 10}, {"link": "dalaeyes.official", "orders": [{"link": "dalaeye-v3", "orders": 8.0}, {"link": "dalaeye-v3", "orders": 2.0}], "visitors": 140, "toCart": 17, "Checkout": 11}, {"link": "dalaeyes.official", "orders": [{"link": "dalaeye-v3", "orders": 5.0}, {"link": "dalaeye-v3", "orders": 1.0}], "visitors": 84, "toCart": 11, "Checkout": 7}, {"link": "dalaeyes.official", "orders": [{"link": "dalaeye-v3", "orders": 8.0}, {"link": "dalaeye-v3", "orders": 2.0}], "visitors": 140, "toCart": 17, "Checkout": 11}, {"link": "dalaeyes.official", "orders": [{"link": "dalaeye-v3", "orders": 8.0}, {"link": "dalaeye-v3", "orders": 2.0}], "visitors": 140, "toCart": 17, "Checkout": 11}, {"link": "dalaeyes.official", "orders": [{"link": "dalaeye-v3", "orders": 7.0}, {"link": "dalaeye-v3", "orders": 2.0}], "visitors": 126, "toCart": 16, "Checkout": 10}, {"link": "dalaeyes.official", "orders": [{"link": "dalaeye-v3", "orders": 4.0}, {"link": "dalaeye-v3", "orders": 1.0}], "visitors": 70, "toCart": 9, "Checkout": 6}, {"link": "dalaeyes.official", "orders": [{"link": "dalaeye-v3", "orders": 2.0}, {"link": "dalaeye-v3", "orders": 1.0}], "visitors": 42, "toCart": 6, "Checkout": 4}, {"link": "dalaeyes.official", "orders": [{"link": "dalaeye-v3", "orders": 1.0}, {"link": "dalaeye-v3", "orders": 0.0}], "visitors": 15, "toCart": 2, "Checkout": 2}, {"link": "dalaeyes.official", "orders": [{"link": "dalaeye-v3", "orders": 2.0}, {"link": "dalaeye-v3", "orders": 1.0}], "visitors": 42, "toCart": 6, "Checkout": 4}, {"link": "dalaeyes.official", "orders": [{"link": "dalaeye-v3", "orders": 1.0}, {"link": "dalaeye-v3", "orders": 0.0}], "visitors": 15, "toCart": 2, "Checkout": 2}, {"link": "dalaeyes.official", "orders": [{"link": "dalaeye-v3", "orders": 2.0}, {"link": "dalaeye-v3", "orders": 0.0}], "visitors": 28, "toCart": 4, "Checkout": 2}]}