{"object": [{"link": "vaberta_official", "orders": [{"link": "vaberta-v3", "orders": 22.0}, {"link": "vaberta-v3", "orders": 5.0}], "visitors": 270, "toCart": 62, "Checkout": 40}, {"link": "vaberta_official", "orders": [{"link": "vaberta-v3", "orders": 18.0}, {"link": "vaberta-v3", "orders": 5.0}], "visitors": 230, "toCart": 53, "Checkout": 34}, {"link": "vaberta_official", "orders": [{"link": "vaberta-v3", "orders": 22.0}, {"link": "vaberta-v3", "orders": 5.0}], "visitors": 270, "toCart": 62, "Checkout": 40}, {"link": "vaberta_official", "orders": [{"link": "vaberta-v3", "orders": 18.0}, {"link": "vaberta-v3", "orders": 5.0}], "visitors": 230, "toCart": 53, "Checkout": 34}, {"link": "vaberta_official", "orders": [{"link": "vaberta-v3", "orders": 18.0}, {"link": "vaberta-v3", "orders": 5.0}], "visitors": 230, "toCart": 53, "Checkout": 34}, {"link": "vaberta_official", "orders": [{"link": "vaberta-v3", "orders": 21.0}, {"link": "vaberta-v3", "orders": 5.0}], "visitors": 260, "toCart": 60, "Checkout": 39}, {"link": "vaberta_official", "orders": [{"link": "vaberta-v3", "orders": 9.0}, {"link": "vaberta-v3", "orders": 2.0}], "visitors": 110, "toCart": 26, "Checkout": 17}, {"link": "vaberta_official", "orders": [{"link": "vaberta-v3", "orders": 12.0}, {"link": "vaberta-v3", "orders": 3.0}], "visitors": 150, "toCart": 35, "Checkout": 23}, {"link": "vaberta_official", "orders": [{"link": "vaberta-v3", "orders": 9.0}, {"link": "vaberta-v3", "orders": 2.0}], "visitors": 110, "toCart": 26, "Checkout": 17}, {"link": "vaberta_official", "orders": [{"link": "vaberta-v3", "orders": 7.0}, {"link": "vaberta-v3", "orders": 2.0}], "visitors": 91, "toCart": 21, "Checkout": 14}, {"link": "vaberta_official", "orders": [{"link": "vaberta-v3", "orders": 9.0}, {"link": "vaberta-v3", "orders": 2.0}], "visitors": 110, "toCart": 26, "Checkout": 17}, {"link": "vaberta_official", "orders": [{"link": "vaberta-v3", "orders": 11.0}, {"link": "vaberta-v3", "orders": 3.0}], "visitors": 141, "toCart": 33, "Checkout": 21}, {"link": "vaberta_official", "orders": [{"link": "vaberta-v3", "orders": 7.0}, {"link": "vaberta-v3", "orders": 2.0}], "visitors": 91, "toCart": 21, "Checkout": 14}, {"link": "vaberta_official", "orders": [{"link": "vaberta-v3", "orders": 11.0}, {"link": "vaberta-v3", "orders": 3.0}], "visitors": 141, "toCart": 33, "Checkout": 21}, {"link": "vaberta_official", "orders": [{"link": "vaberta-v3", "orders": 11.0}, {"link": "vaberta-v3", "orders": 3.0}], "visitors": 141, "toCart": 33, "Checkout": 21}, {"link": "vaberta_official", "orders": [{"link": "vaberta-v3", "orders": 11.0}, {"link": "vaberta-v3", "orders": 3.0}], "visitors": 141, "toCart": 33, "Checkout": 21}, {"link": "vaberta_official", "orders": [{"link": "vaberta-v3", "orders": 10.0}, {"link": "vaberta-v3", "orders": 3.0}], "visitors": 130, "toCart": 30, "Checkout": 20}, {"link": "vaberta_official", "orders": [{"link": "vaberta-v3", "orders": 7.0}, {"link": "vaberta-v3", "orders": 2.0}], "visitors": 91, "toCart": 21, "Checkout": 14}, {"link": "vaberta_official", "orders": [{"link": "vaberta-v3", "orders": 12.0}, {"link": "vaberta-v3", "orders": 3.0}], "visitors": 150, "toCart": 35, "Checkout": 23}, {"link": "vaberta_official", "orders": [{"link": "vaberta-v3", "orders": 2.0}, {"link": "vaberta-v3", "orders": 0.0}], "visitors": 21, "toCart": 5, "Checkout": 4}, {"link": "vaberta_official", "orders": [{"link": "vaberta-v3", "orders": 4.0}, {"link": "vaberta-v3", "orders": 1.0}], "visitors": 51, "toCart": 12, "Checkout": 8}, {"link": "vaberta_official", "orders": [{"link": "vaberta-v3", "orders": 1.0}, {"link": "vaberta-v3", "orders": 0.0}], "visitors": 11, "toCart": 3, "Checkout": 2}, {"link": "vaberta_official", "orders": [{"link": "vaberta-v3", "orders": 2.0}, {"link": "vaberta-v3", "orders": 0.0}], "visitors": 21, "toCart": 5, "Checkout": 4}, {"link": "vaberta_official", "orders": [{"link": "vaberta-v3", "orders": 4.0}, {"link": "vaberta-v3", "orders": 1.0}], "visitors": 51, "toCart": 12, "Checkout": 8}]}