{"object": [{"link": "dandyhair.official", "orders": [{"link": "dandyhair-v3", "orders": 7.0}, {"link": "dandyhair-v3", "orders": 2.0}], "visitors": 159, "toCart": 19, "Checkout": 13}, {"link": "dandyhair.official", "orders": [{"link": "dandyhair-v3", "orders": 9.0}, {"link": "dandyhair-v3", "orders": 2.0}], "visitors": 195, "toCart": 24, "Checkout": 16}, {"link": "dandyhair.official", "orders": [{"link": "dandyhair-v3", "orders": 8.0}, {"link": "dandyhair-v3", "orders": 2.0}], "visitors": 178, "toCart": 22, "Checkout": 14}, {"link": "dandyhair.official", "orders": [{"link": "dandyhair-v3", "orders": 8.0}, {"link": "dandyhair-v3", "orders": 2.0}], "visitors": 178, "toCart": 22, "Checkout": 14}, {"link": "dandyhair.official", "orders": [{"link": "dandyhair-v3", "orders": 7.0}, {"link": "dandyhair-v3", "orders": 2.0}], "visitors": 159, "toCart": 19, "Checkout": 13}, {"link": "dandyhair.official", "orders": [{"link": "dandyhair-v3", "orders": 9.0}, {"link": "dandyhair-v3", "orders": 2.0}], "visitors": 195, "toCart": 24, "Checkout": 16}, {"link": "dandyhair.official", "orders": [{"link": "dandyhair-v3", "orders": 3.0}, {"link": "dandyhair-v3", "orders": 1.0}], "visitors": 72, "toCart": 9, "Checkout": 6}, {"link": "dandyhair.official", "orders": [{"link": "dandyhair-v3", "orders": 3.0}, {"link": "dandyhair-v3", "orders": 1.0}], "visitors": 72, "toCart": 9, "Checkout": 6}, {"link": "dandyhair.official", "orders": [{"link": "dandyhair-v3", "orders": 4.0}, {"link": "dandyhair-v3", "orders": 1.0}], "visitors": 89, "toCart": 11, "Checkout": 7}, {"link": "dandyhair.official", "orders": [{"link": "dandyhair-v3", "orders": 3.0}, {"link": "dandyhair-v3", "orders": 1.0}], "visitors": 72, "toCart": 9, "Checkout": 6}, {"link": "dandyhair.official", "orders": [{"link": "dandyhair-v3", "orders": 4.0}, {"link": "dandyhair-v3", "orders": 1.0}], "visitors": 89, "toCart": 11, "Checkout": 7}, {"link": "dandyhair.official", "orders": [{"link": "dandyhair-v3", "orders": 4.0}, {"link": "dandyhair-v3", "orders": 1.0}], "visitors": 89, "toCart": 11, "Checkout": 7}, {"link": "dandyhair.official", "orders": [{"link": "dandyhair-v3", "orders": 3.0}, {"link": "dandyhair-v3", "orders": 1.0}], "visitors": 72, "toCart": 9, "Checkout": 6}, {"link": "dandyhair.official", "orders": [{"link": "dandyhair-v3", "orders": 5.0}, {"link": "dandyhair-v3", "orders": 1.0}], "visitors": 107, "toCart": 13, "Checkout": 9}, {"link": "dandyhair.official", "orders": [{"link": "dandyhair-v3", "orders": 3.0}, {"link": "dandyhair-v3", "orders": 1.0}], "visitors": 72, "toCart": 9, "Checkout": 6}, {"link": "dandyhair.official", "orders": [{"link": "dandyhair-v3", "orders": 4.0}, {"link": "dandyhair-v3", "orders": 1.0}], "visitors": 89, "toCart": 11, "Checkout": 7}, {"link": "dandyhair.official", "orders": [{"link": "dandyhair-v3", "orders": 3.0}, {"link": "dandyhair-v3", "orders": 1.0}], "visitors": 72, "toCart": 9, "Checkout": 6}, {"link": "dandyhair.official", "orders": [{"link": "dandyhair-v3", "orders": 4.0}, {"link": "dandyhair-v3", "orders": 1.0}], "visitors": 89, "toCart": 11, "Checkout": 7}, {"link": "dandyhair.official", "orders": [{"link": "dandyhair-v3", "orders": 4.0}, {"link": "dandyhair-v3", "orders": 1.0}], "visitors": 89, "toCart": 11, "Checkout": 7}, {"link": "dandyhair.official", "orders": [{"link": "dandyhair-v3", "orders": 1.0}, {"link": "dandyhair-v3", "orders": 0.0}], "visitors": 18, "toCart": 3, "Checkout": 2}, {"link": "dandyhair.official", "orders": [{"link": "dandyhair-v3", "orders": 1.0}, {"link": "dandyhair-v3", "orders": 0.0}], "visitors": 18, "toCart": 3, "Checkout": 2}, {"link": "dandyhair.official", "orders": [{"link": "dandyhair-v3", "orders": 2.0}, {"link": "dandyhair-v3", "orders": 0.0}], "visitors": 36, "toCart": 5, "Checkout": 3}, {"link": "dandyhair.official", "orders": [{"link": "dandyhair-v3", "orders": 1.0}, {"link": "dandyhair-v3", "orders": 0.0}], "visitors": 18, "toCart": 3, "Checkout": 2}, {"link": "dandyhair.official", "orders": [{"link": "dandyhair-v3", "orders": 1.0}, {"link": "dandyhair-v3", "orders": 0.0}], "visitors": 18, "toCart": 3, "Checkout": 2}]}