{"object": [{"link": "dandyhair.official", "orders": [{"link": "dandyhair-v3", "orders": 8.0}, {"link": "dandyhair-v3", "orders": 2.0}], "visitors": 119, "toCart": 9, "Checkout": 11}, {"link": "dandyhair.official", "orders": [{"link": "dandyhair-v3", "orders": 8.0}, {"link": "dandyhair-v3", "orders": 2.0}], "visitors": 119, "toCart": 9, "Checkout": 11}, {"link": "dandyhair.official", "orders": [{"link": "dandyhair-v3", "orders": 9.0}, {"link": "dandyhair-v3", "orders": 2.0}], "visitors": 131, "toCart": 10, "Checkout": 13}, {"link": "dandyhair.official", "orders": [{"link": "dandyhair-v3", "orders": 9.0}, {"link": "dandyhair-v3", "orders": 2.0}], "visitors": 131, "toCart": 10, "Checkout": 13}, {"link": "dandyhair.official", "orders": [{"link": "dandyhair-v3", "orders": 8.0}, {"link": "dandyhair-v3", "orders": 2.0}], "visitors": 119, "toCart": 9, "Checkout": 11}, {"link": "dandyhair.official", "orders": [{"link": "dandyhair-v3", "orders": 9.0}, {"link": "dandyhair-v3", "orders": 2.0}], "visitors": 131, "toCart": 10, "Checkout": 13}, {"link": "dandyhair.official", "orders": [{"link": "dandyhair-v3", "orders": 4.0}, {"link": "dandyhair-v3", "orders": 1.0}], "visitors": 60, "toCart": 5, "Checkout": 6}, {"link": "dandyhair.official", "orders": [{"link": "dandyhair-v3", "orders": 4.0}, {"link": "dandyhair-v3", "orders": 1.0}], "visitors": 60, "toCart": 5, "Checkout": 6}, {"link": "dandyhair.official", "orders": [{"link": "dandyhair-v3", "orders": 3.0}, {"link": "dandyhair-v3", "orders": 1.0}], "visitors": 48, "toCart": 4, "Checkout": 5}, {"link": "dandyhair.official", "orders": [{"link": "dandyhair-v3", "orders": 3.0}, {"link": "dandyhair-v3", "orders": 1.0}], "visitors": 48, "toCart": 4, "Checkout": 5}, {"link": "dandyhair.official", "orders": [{"link": "dandyhair-v3", "orders": 5.0}, {"link": "dandyhair-v3", "orders": 1.0}], "visitors": 72, "toCart": 6, "Checkout": 7}, {"link": "dandyhair.official", "orders": [{"link": "dandyhair-v3", "orders": 3.0}, {"link": "dandyhair-v3", "orders": 1.0}], "visitors": 48, "toCart": 4, "Checkout": 5}, {"link": "dandyhair.official", "orders": [{"link": "dandyhair-v3", "orders": 4.0}, {"link": "dandyhair-v3", "orders": 1.0}], "visitors": 60, "toCart": 5, "Checkout": 6}, {"link": "dandyhair.official", "orders": [{"link": "dandyhair-v3", "orders": 4.0}, {"link": "dandyhair-v3", "orders": 1.0}], "visitors": 60, "toCart": 5, "Checkout": 6}, {"link": "dandyhair.official", "orders": [{"link": "dandyhair-v3", "orders": 4.0}, {"link": "dandyhair-v3", "orders": 1.0}], "visitors": 60, "toCart": 5, "Checkout": 6}, {"link": "dandyhair.official", "orders": [{"link": "dandyhair-v3", "orders": 4.0}, {"link": "dandyhair-v3", "orders": 1.0}], "visitors": 60, "toCart": 5, "Checkout": 6}, {"link": "dandyhair.official", "orders": [{"link": "dandyhair-v3", "orders": 6.0}, {"link": "dandyhair-v3", "orders": 2.0}], "visitors": 96, "toCart": 8, "Checkout": 9}, {"link": "dandyhair.official", "orders": [{"link": "dandyhair-v3", "orders": 4.0}, {"link": "dandyhair-v3", "orders": 1.0}], "visitors": 60, "toCart": 5, "Checkout": 6}, {"link": "dandyhair.official", "orders": [{"link": "dandyhair-v3", "orders": 5.0}, {"link": "dandyhair-v3", "orders": 1.0}], "visitors": 72, "toCart": 6, "Checkout": 7}, {"link": "dandyhair.official", "orders": [{"link": "dandyhair-v3", "orders": 1.0}, {"link": "dandyhair-v3", "orders": 0.0}], "visitors": 12, "toCart": 1, "Checkout": 2}, {"link": "dandyhair.official", "orders": [{"link": "dandyhair-v3", "orders": 1.0}, {"link": "dandyhair-v3", "orders": 0.0}], "visitors": 12, "toCart": 1, "Checkout": 2}, {"link": "dandyhair.official", "orders": [{"link": "dandyhair-v3", "orders": 2.0}, {"link": "dandyhair-v3", "orders": 0.0}], "visitors": 24, "toCart": 2, "Checkout": 3}, {"link": "dandyhair.official", "orders": [{"link": "dandyhair-v3", "orders": 0.0}, {"link": "dandyhair-v3", "orders": 0.0}], "visitors": 0, "toCart": 0, "Checkout": 0}, {"link": "dandyhair.official", "orders": [{"link": "dandyhair-v3", "orders": 1.0}, {"link": "dandyhair-v3", "orders": 0.0}], "visitors": 12, "toCart": 1, "Checkout": 2}]}