{"object": [{"link": "dandyhair.official", "orders": [{"link": "dandyhair-v3", "orders": 6.0}, {"link": "dandyhair-v3", "orders": 1.0}], "visitors": 148, "toCart": 10, "Checkout": 8}, {"link": "dandyhair.official", "orders": [{"link": "dandyhair-v3", "orders": 6.0}, {"link": "dandyhair-v3", "orders": 1.0}], "visitors": 148, "toCart": 10, "Checkout": 8}, {"link": "dandyhair.official", "orders": [{"link": "dandyhair-v3", "orders": 5.0}, {"link": "dandyhair-v3", "orders": 1.0}], "visitors": 126, "toCart": 8, "Checkout": 7}, {"link": "dandyhair.official", "orders": [{"link": "dandyhair-v3", "orders": 6.0}, {"link": "dandyhair-v3", "orders": 1.0}], "visitors": 148, "toCart": 10, "Checkout": 8}, {"link": "dandyhair.official", "orders": [{"link": "dandyhair-v3", "orders": 5.0}, {"link": "dandyhair-v3", "orders": 1.0}], "visitors": 126, "toCart": 8, "Checkout": 7}, {"link": "dandyhair.official", "orders": [{"link": "dandyhair-v3", "orders": 5.0}, {"link": "dandyhair-v3", "orders": 1.0}], "visitors": 126, "toCart": 8, "Checkout": 7}, {"link": "dandyhair.official", "orders": [{"link": "dandyhair-v3", "orders": 3.0}, {"link": "dandyhair-v3", "orders": 1.0}], "visitors": 85, "toCart": 6, "Checkout": 5}, {"link": "dandyhair.official", "orders": [{"link": "dandyhair-v3", "orders": 2.0}, {"link": "dandyhair-v3", "orders": 0.0}], "visitors": 43, "toCart": 3, "Checkout": 3}, {"link": "dandyhair.official", "orders": [{"link": "dandyhair-v3", "orders": 2.0}, {"link": "dandyhair-v3", "orders": 1.0}], "visitors": 63, "toCart": 4, "Checkout": 4}, {"link": "dandyhair.official", "orders": [{"link": "dandyhair-v3", "orders": 3.0}, {"link": "dandyhair-v3", "orders": 1.0}], "visitors": 85, "toCart": 6, "Checkout": 5}, {"link": "dandyhair.official", "orders": [{"link": "dandyhair-v3", "orders": 2.0}, {"link": "dandyhair-v3", "orders": 0.0}], "visitors": 43, "toCart": 3, "Checkout": 3}, {"link": "dandyhair.official", "orders": [{"link": "dandyhair-v3", "orders": 3.0}, {"link": "dandyhair-v3", "orders": 1.0}], "visitors": 85, "toCart": 6, "Checkout": 5}, {"link": "dandyhair.official", "orders": [{"link": "dandyhair-v3", "orders": 2.0}, {"link": "dandyhair-v3", "orders": 1.0}], "visitors": 63, "toCart": 4, "Checkout": 4}, {"link": "dandyhair.official", "orders": [{"link": "dandyhair-v3", "orders": 2.0}, {"link": "dandyhair-v3", "orders": 1.0}], "visitors": 63, "toCart": 4, "Checkout": 4}, {"link": "dandyhair.official", "orders": [{"link": "dandyhair-v3", "orders": 2.0}, {"link": "dandyhair-v3", "orders": 1.0}], "visitors": 63, "toCart": 4, "Checkout": 4}, {"link": "dandyhair.official", "orders": [{"link": "dandyhair-v3", "orders": 3.0}, {"link": "dandyhair-v3", "orders": 1.0}], "visitors": 85, "toCart": 6, "Checkout": 5}, {"link": "dandyhair.official", "orders": [{"link": "dandyhair-v3", "orders": 3.0}, {"link": "dandyhair-v3", "orders": 1.0}], "visitors": 85, "toCart": 6, "Checkout": 5}, {"link": "dandyhair.official", "orders": [{"link": "dandyhair-v3", "orders": 2.0}, {"link": "dandyhair-v3", "orders": 0.0}], "visitors": 43, "toCart": 3, "Checkout": 3}, {"link": "dandyhair.official", "orders": [{"link": "dandyhair-v3", "orders": 3.0}, {"link": "dandyhair-v3", "orders": 1.0}], "visitors": 85, "toCart": 6, "Checkout": 5}, {"link": "dandyhair.official", "orders": [{"link": "dandyhair-v3", "orders": 0.0}, {"link": "dandyhair-v3", "orders": 0.0}], "visitors": 0, "toCart": 0, "Checkout": 0}, {"link": "dandyhair.official", "orders": [{"link": "dandyhair-v3", "orders": 1.0}, {"link": "dandyhair-v3", "orders": 0.0}], "visitors": 21, "toCart": 2, "Checkout": 2}, {"link": "dandyhair.official", "orders": [{"link": "dandyhair-v3", "orders": 1.0}, {"link": "dandyhair-v3", "orders": 0.0}], "visitors": 21, "toCart": 2, "Checkout": 2}, {"link": "dandyhair.official", "orders": [{"link": "dandyhair-v3", "orders": 0.0}, {"link": "dandyhair-v3", "orders": 0.0}], "visitors": 0, "toCart": 0, "Checkout": 0}, {"link": "dandyhair.official", "orders": [{"link": "dandyhair-v3", "orders": 1.0}, {"link": "dandyhair-v3", "orders": 0.0}], "visitors": 21, "toCart": 2, "Checkout": 2}]}