{"object": [{"link": "zarqon.official", "orders": [{"link": "zarqone-v2", "orders": 19.0}, {"link": "zarqone-v2", "orders": 5.0}], "visitors": 361, "toCart": 45, "Checkout": 30}, {"link": "zarqon.official", "orders": [{"link": "zarqone-v2", "orders": 22.0}, {"link": "zarqone-v2", "orders": 6.0}], "visitors": 421, "toCart": 53, "Checkout": 34}, {"link": "zarqon.official", "orders": [{"link": "zarqone-v2", "orders": 19.0}, {"link": "zarqone-v2", "orders": 5.0}], "visitors": 361, "toCart": 45, "Checkout": 30}, {"link": "zarqon.official", "orders": [{"link": "zarqone-v2", "orders": 20.0}, {"link": "zarqone-v2", "orders": 5.0}], "visitors": 376, "toCart": 47, "Checkout": 31}, {"link": "zarqon.official", "orders": [{"link": "zarqone-v2", "orders": 20.0}, {"link": "zarqone-v2", "orders": 5.0}], "visitors": 376, "toCart": 47, "Checkout": 31}, {"link": "zarqon.official", "orders": [{"link": "zarqone-v2", "orders": 20.0}, {"link": "zarqone-v2", "orders": 5.0}], "visitors": 376, "toCart": 47, "Checkout": 31}, {"link": "zarqon.official", "orders": [{"link": "zarqone-v2", "orders": 12.0}, {"link": "zarqone-v2", "orders": 3.0}], "visitors": 225, "toCart": 28, "Checkout": 19}, {"link": "zarqon.official", "orders": [{"link": "zarqone-v2", "orders": 11.0}, {"link": "zarqone-v2", "orders": 3.0}], "visitors": 211, "toCart": 27, "Checkout": 17}, {"link": "zarqon.official", "orders": [{"link": "zarqone-v2", "orders": 14.0}, {"link": "zarqone-v2", "orders": 3.0}], "visitors": 255, "toCart": 32, "Checkout": 21}, {"link": "zarqon.official", "orders": [{"link": "zarqone-v2", "orders": 12.0}, {"link": "zarqone-v2", "orders": 3.0}], "visitors": 225, "toCart": 28, "Checkout": 19}, {"link": "zarqon.official", "orders": [{"link": "zarqone-v2", "orders": 13.0}, {"link": "zarqone-v2", "orders": 3.0}], "visitors": 240, "toCart": 30, "Checkout": 20}, {"link": "zarqon.official", "orders": [{"link": "zarqone-v2", "orders": 12.0}, {"link": "zarqone-v2", "orders": 3.0}], "visitors": 225, "toCart": 28, "Checkout": 19}, {"link": "zarqon.official", "orders": [{"link": "zarqone-v2", "orders": 13.0}, {"link": "zarqone-v2", "orders": 3.0}], "visitors": 240, "toCart": 30, "Checkout": 20}, {"link": "zarqon.official", "orders": [{"link": "zarqone-v2", "orders": 8.0}, {"link": "zarqone-v2", "orders": 2.0}], "visitors": 151, "toCart": 19, "Checkout": 13}, {"link": "zarqon.official", "orders": [{"link": "zarqone-v2", "orders": 12.0}, {"link": "zarqone-v2", "orders": 3.0}], "visitors": 225, "toCart": 28, "Checkout": 19}, {"link": "zarqon.official", "orders": [{"link": "zarqone-v2", "orders": 11.0}, {"link": "zarqone-v2", "orders": 3.0}], "visitors": 211, "toCart": 27, "Checkout": 17}, {"link": "zarqon.official", "orders": [{"link": "zarqone-v2", "orders": 12.0}, {"link": "zarqone-v2", "orders": 3.0}], "visitors": 225, "toCart": 28, "Checkout": 19}, {"link": "zarqon.official", "orders": [{"link": "zarqone-v2", "orders": 10.0}, {"link": "zarqone-v2", "orders": 2.0}], "visitors": 181, "toCart": 23, "Checkout": 15}, {"link": "zarqon.official", "orders": [{"link": "zarqone-v2", "orders": 7.0}, {"link": "zarqone-v2", "orders": 2.0}], "visitors": 136, "toCart": 17, "Checkout": 11}, {"link": "zarqon.official", "orders": [{"link": "zarqone-v2", "orders": 2.0}, {"link": "zarqone-v2", "orders": 1.0}], "visitors": 45, "toCart": 6, "Checkout": 4}, {"link": "zarqon.official", "orders": [{"link": "zarqone-v2", "orders": 3.0}, {"link": "zarqone-v2", "orders": 1.0}], "visitors": 60, "toCart": 8, "Checkout": 5}, {"link": "zarqon.official", "orders": [{"link": "zarqone-v2", "orders": 3.0}, {"link": "zarqone-v2", "orders": 1.0}], "visitors": 60, "toCart": 8, "Checkout": 5}, {"link": "zarqon.official", "orders": [{"link": "zarqone-v2", "orders": 4.0}, {"link": "zarqone-v2", "orders": 1.0}], "visitors": 75, "toCart": 10, "Checkout": 6}, {"link": "zarqon.official", "orders": [{"link": "zarqone-v2", "orders": 2.0}, {"link": "zarqone-v2", "orders": 1.0}], "visitors": 45, "toCart": 6, "Checkout": 4}]}